CHANGES.txt
DEPENDENCES.txt
README.txt
setup.py
src/ng/__init__.py
src/ng.site.npclider.egg-info/PKG-INFO
src/ng.site.npclider.egg-info/SOURCES.txt
src/ng.site.npclider.egg-info/dependency_links.txt
src/ng.site.npclider.egg-info/namespace_packages.txt
src/ng.site.npclider.egg-info/not-zip-safe
src/ng.site.npclider.egg-info/requires.txt
src/ng.site.npclider.egg-info/top_level.txt
src/ng/site/__init__.py
src/ng/site/npclider/__init__.py
src/ng/site/npclider/configure.zcml
src/ng/site/npclider/ng.site.npclider.txt
src/ng/site/npclider/etc/ng.site.npclider-configure.zcml
src/ng/site/npclider/etc/ng.site.npclider-meta.zcml
src/ng/site/npclider/projectannotation/__init__.py
src/ng/site/npclider/projectannotation/configure.zcml
src/ng/site/npclider/projectannotation/interfaces.py
src/ng/site/npclider/projectannotation/projectannotation.py
src/ng/site/npclider/projectannotation/projectannotationableadapter.py
src/ng/site/npclider/projectannotation/browser/__init__.py
src/ng/site/npclider/projectannotation/browser/configure.zcml